README.md
setup.py
terraform_null_provider_wrapper.py
terraform_null_provider_wrapper.egg-info/PKG-INFO
terraform_null_provider_wrapper.egg-info/SOURCES.txt
terraform_null_provider_wrapper.egg-info/dependency_links.txt
terraform_null_provider_wrapper.egg-info/entry_points.txt
terraform_null_provider_wrapper.egg-info/top_level.txt