Metadata-Version: 1.0
Name: terraform-null-provider-wrapper
Version: 2.1.2.post3
Summary: Python wrapper for Terraform Null Provider
Home-page: https://github.com/imanazari70/terraform-null-provider-wrapper
Author: Iman Azari
Author-email: azari@mahsan.co
License: UNKNOWN
Platform: UNKNOWN
